plottable/__init__.py
plottable/cell.py
plottable/cmap.py
plottable/column_def.py
plottable/font.py
plottable/formatters.py
plottable/helpers.py
plottable/plots.py
plottable/table.py
tests/__init__.py
tests/conftest.py
tests/test_cell.py
tests/test_cmap.py
tests/test_column_def.py
tests/test_font.py
tests/test_formatters.py
tests/test_helpers.py
tests/test_table.py
plottable-0.1.5.dist-info/LICENSE.txt
plottable-0.1.5.dist-info/METADATA
plottable-0.1.5.dist-info/WHEEL
plottable-0.1.5.dist-info/top_level.txt
plottable-0.1.5.dist-info/RECORD
