Metadata-Version: 2.1
Name: plottable
Version: 0.1.5
Summary: Beautifully customized tables with matplotlib
Home-page: https://github.com/znstrider/plottable
Author: znstrider
Author-email: mindfulstrider@gmail.com
License: MIT
Classifier: Development Status :: 3 - Alpha
Classifier: Intended Audience :: Science/Research
Classifier: Programming Language :: Python :: 3.7
Classifier: Programming Language :: Python :: 3.8
Classifier: Programming Language :: Python :: 3.9
Classifier: Programming Language :: Python :: 3.10
Classifier: Programming Language :: Python :: 3.11
Classifier: Framework :: Matplotlib
Classifier: Topic :: Scientific/Engineering :: Visualization
Requires-Python: >=3.7
Provides-Extra: development
License-File: LICENSE.txt
